raisenow/__init__.py
raisenow/raisenow.py
raisenow-0.1.1.dist-info/WHEEL
raisenow-0.1.1.dist-info/METADATA
raisenow-0.1.1.dist-info/RECORD
