Metadata-Version: 2.1
Name: raisenow
Version: 0.1.1
Summary: A python library to interact with the RaiseNow API
License: MIT
Author: Martin Mohnhaupt
Author-email: m.mohnhaupt@bluewin.ch
Maintainer: Martin Mohnhaupt
Maintainer-email: m.mohnhaupt@bluewin.ch
Requires-Python: >=3.8,<4.0
Classifier: License :: OSI Approved :: MIT License
Classifier: Programming Language :: Python :: 3
Classifier: Programming Language :: Python :: 3.8
Classifier: Programming Language :: Python :: 3.9
Classifier: Programming Language :: Python :: 3.10
Classifier: Programming Language :: Python :: 3.11
Requires-Dist: urllib3 (>=1.26.12,<2.0.0)
